README.txt
__init__.py
setup.cfg
setup.py
docs/install.txt
docs/readme.rtf
pypdf2table/Column.py
pypdf2table/ExecuteConverter.py
pypdf2table/FirstClassification.py
pypdf2table/Font.py
pypdf2table/GetOutputFilePathList.py
pypdf2table/GetOutputStringIOList.py
pypdf2table/IProxyXMLFileReallocator.py
pypdf2table/LeftComparator.py
pypdf2table/Line.py
pypdf2table/MultilineBlock.py
pypdf2table/MyNode.py
pypdf2table/Output.py
pypdf2table/SecondClassification.py
pypdf2table/Table.py
pypdf2table/TextColumn.py
pypdf2table/TextElement.py
pypdf2table/TopComparator.py
pypdf2table/TopComparatorForTexts.py
pypdf2table/__init__.py
pypdf2table/fileMover.py
pypdf2table.egg-info/PKG-INFO
pypdf2table.egg-info/SOURCES.txt
pypdf2table.egg-info/dependency_links.txt
pypdf2table.egg-info/entry_points.txt
pypdf2table.egg-info/not-zip-safe
pypdf2table.egg-info/requires.txt
pypdf2table.egg-info/top_level.txt
tests/__init__.py
tests/testExecuteConverter.py
tests/files/Yildiz_MasterThesis.pdf
tests/files/componentes.pdf
tests/files/diesel.pdf
tests/files/farmaciapopular.pdf
tests/files/farmaciapopular.xml
tests/files/mestrado-rodrigo.pdf
tests/files/monografia_ronaldo.pdf
tests/files/precos.pdf
tests/files/premioprofessor.pdf
tests/files/premioprofessor.xml