Metadata-Version: 1.0
Name: pypdf2table
Version: 0.2.2
Summary: PDF table extraction tool
Home-page: http://nsi.iff.edu.br
Author: Vanderson Mota dos Santos
Author-email: vanderson.mota@gmail.com
License: UNKNOWN
Platform: UNKNOWN
